pure_graph_of_thoughts/__init__.py
pure_graph_of_thoughts/py.typed
pure_graph_of_thoughts/api/__init__.py
pure_graph_of_thoughts/api/controller/__init__.py
pure_graph_of_thoughts/api/controller/controller.py
pure_graph_of_thoughts/api/controller/graph_of_operations_execution.py
pure_graph_of_thoughts/api/graph/__init__.py
pure_graph_of_thoughts/api/graph/graph.py
pure_graph_of_thoughts/api/graph/graph_schema.py
pure_graph_of_thoughts/api/graph/node.py
pure_graph_of_thoughts/api/graph/node_schema.py
pure_graph_of_thoughts/api/graph/operation/__init__.py
pure_graph_of_thoughts/api/graph/operation/graph_of_operations.py
pure_graph_of_thoughts/api/graph/operation/operation_array.py
pure_graph_of_thoughts/api/graph/operation/operation_graph_schema.py
pure_graph_of_thoughts/api/graph/operation/operation_node.py
pure_graph_of_thoughts/api/graph/operation/operation_node_schema.py
pure_graph_of_thoughts/api/graph/thought/__init__.py
pure_graph_of_thoughts/api/graph/thought/graph_of_thoughts.py
pure_graph_of_thoughts/api/graph/thought/thought_graph_schema.py
pure_graph_of_thoughts/api/graph/thought/thought_node.py
pure_graph_of_thoughts/api/graph/thought/thought_node_schema.py
pure_graph_of_thoughts/api/internal/__init__.py
pure_graph_of_thoughts/api/internal/id/__init__.py
pure_graph_of_thoughts/api/internal/id/id.py
pure_graph_of_thoughts/api/internal/id/id_from_str.py
pure_graph_of_thoughts/api/internal/id/id_generator.py
pure_graph_of_thoughts/api/internal/id/identifiable.py
pure_graph_of_thoughts/api/internal/seal/__init__.py
pure_graph_of_thoughts/api/internal/seal/mutating.py
pure_graph_of_thoughts/api/internal/seal/sealable.py
pure_graph_of_thoughts/api/internal/seal/sealed_exception.py
pure_graph_of_thoughts/api/language_model/__init__.py
pure_graph_of_thoughts/api/language_model/example.py
pure_graph_of_thoughts/api/language_model/language_model.py
pure_graph_of_thoughts/api/language_model/prompt.py
pure_graph_of_thoughts/api/operation/__init__.py
pure_graph_of_thoughts-1.3.0.dist-info/METADATA
pure_graph_of_thoughts-1.3.0.dist-info/WHEEL
pure_graph_of_thoughts-1.3.0.dist-info/licenses/LICENSE
pure_graph_of_thoughts-1.3.0.dist-info/RECORD
