Metadata-Version: 2.4
Name: pure-graph-of-thoughts
Version: 1.3.0
Summary: Pure Graph of Thoughts
Project-URL: Repository, https://github.com/mriesen/pure-graph-of-thoughts.git
Author-email: Manuel Riesen <manuel.riesen0@gmail.com>
Maintainer-email: Manuel Riesen <manuel.riesen0@gmail.com>
License-File: LICENSE
Classifier: Development Status :: 3 - Alpha
Classifier: Programming Language :: Python
Classifier: Programming Language :: Python :: 3.11
Classifier: Programming Language :: Python :: 3.12
Classifier: Topic :: Scientific/Engineering :: Artificial Intelligence
Requires-Python: >=3.11
Requires-Dist: backoff<3.0.0,>=2.2.1
Requires-Dist: openai<2.0.0,>=1.12.0
Provides-Extra: notebooks
Requires-Dist: jupyter<2.0.0,>=1.0.0; extra == 'notebooks'
Provides-Extra: visualization
Requires-Dist: matplotlib<4.0.0,>=3.8.3; extra == 'visualization'
Requires-Dist: networkx<4.0.0,>=3.2.1; extra == 'visualization'
Requires-Dist: types-networkx<4.0.0,>=3.2.1; extra == 'visualization'
Provides-Extra: visualization-dot
Requires-Dist: pygraphviz<2.0,>=1.12; extra == 'visualization-dot'
